TensorflowTutorialsPkmital/README.md
TensorflowTutorialsPkmital/__init__.py
TensorflowTutorialsPkmital/__main__.py
TensorflowTutorialsPkmital/file.epub
TensorflowTutorialsPkmital/index.html
TensorflowTutorialsPkmital/css/__init__.py
TensorflowTutorialsPkmital/css/annotations.css
TensorflowTutorialsPkmital/css/main.css
TensorflowTutorialsPkmital/css/normalize.css
TensorflowTutorialsPkmital/css/popup.css
TensorflowTutorialsPkmital/font/__init__.py
TensorflowTutorialsPkmital/font/fontello.eot
TensorflowTutorialsPkmital/font/fontello.svg
TensorflowTutorialsPkmital/font/fontello.ttf
TensorflowTutorialsPkmital/font/fontello.woff
TensorflowTutorialsPkmital/img/__init__.py
TensorflowTutorialsPkmital/img/annotator-glyph-sprite.png
TensorflowTutorialsPkmital/img/annotator-icon-sprite.png
TensorflowTutorialsPkmital/img/apple-touch-icon.png
TensorflowTutorialsPkmital/img/cancelfullscreen.png
TensorflowTutorialsPkmital/img/close.png
TensorflowTutorialsPkmital/img/fullscreen.png
TensorflowTutorialsPkmital/img/loader.gif
TensorflowTutorialsPkmital/img/menu-icon.png
TensorflowTutorialsPkmital/img/save.png
TensorflowTutorialsPkmital/img/saved.png
TensorflowTutorialsPkmital/img/settings-s.png
TensorflowTutorialsPkmital/img/settings.png
TensorflowTutorialsPkmital/img/star.png
TensorflowTutorialsPkmital/js/__init__.py
TensorflowTutorialsPkmital/js/epub.js
TensorflowTutorialsPkmital/js/epub.min.js
TensorflowTutorialsPkmital/js/epub.min.map
TensorflowTutorialsPkmital/js/hooks.min.js
TensorflowTutorialsPkmital/js/hooks.min.map
TensorflowTutorialsPkmital/js/reader.js
TensorflowTutorialsPkmital/js/reader.js.map
TensorflowTutorialsPkmital/js/reader.min.js
TensorflowTutorialsPkmital/js/reader.min.map
TensorflowTutorialsPkmital/js/hooks/__init__.py
TensorflowTutorialsPkmital/js/hooks/extensions/__init__.py
TensorflowTutorialsPkmital/js/hooks/extensions/highlight.js
TensorflowTutorialsPkmital/js/libs/__init__.py
TensorflowTutorialsPkmital/js/libs/jquery.min.js
tensorflow_tutorials_pkmital-2024.3.3.0.dist-info/METADATA
tensorflow_tutorials_pkmital-2024.3.3.0.dist-info/WHEEL
tensorflow_tutorials_pkmital-2024.3.3.0.dist-info/entry_points.txt
tensorflow_tutorials_pkmital-2024.3.3.0.dist-info/top_level.txt
tensorflow_tutorials_pkmital-2024.3.3.0.dist-info/RECORD
